{
    "initializationAction": [
        "c.npc.set_chatting();",
        "q.run_command('scoreboard players set ' + q.player.username + ' BattleEnd 2');",
        "q.run_command('execute as ' + q.player.username + ' run function johto:tools/forceclick');",
        "q.run_command('execute as ' + q.player.username + ' run tag ' + q.player.username + ' add Bugsy');",
        "q.run_command('tellraw ' + q.player.username + ' {\"text\":\"You got $1,800 for winning!\",\"italic\":true,\"color\":\"gray\"}');",
        "q.run_command('scoreboard players add ' + q.player.username + ' Money 1800');"
    ],
    "speakers": {
        "npc": {
            "name": "Bugsy",
            "face": {
                "type": "artificial",
                "modelType": "npc",
                "identifier": "cobblemon:bugsy",
                "isLeftSide": true
            }
        }
    },
    "pages": [
        {
            "id": "greeting",
            "speaker": "npc",
            "lines": [
                "Whoa, amazing! You're an expert on Pokémon! My research isn't complete yet. OK, you win."
            ],
            "input": {
                "type": "option",
                "vertical": false,
                "options": [
                    {
                        "text": "Next",
                        "value": "next",
                        "action": "q.dialogue.set_page('page2');"
                    }
                ]
            }
        },
        {
            "id": "page2",
            "speaker": "npc",
            "lines": [
                "Bug-type Pokémon are deep. There are many mysteries to explore. Study your top choices thoroughly."
            ],
            "input": {
                "type": "option",
                "vertical": false,
                "options": [
                    {
                        "text": "Close",
                        "value": "close",
                        "action": [
                            "q.run_command('execute as ' + q.player.username + ' run advancement grant @s only johto:badges/badge2');",
                            "q.dialogue.close();"
                        ]
                    }
                ]
            }
        }
    ],
    "escapeAction": []
}