{
    "hitbox": "player",
    "resourceIdentifier": "cobblemon:blue",
    "autoHealParty": true,
    "isMovable": false,
    "isLeashable": false,
    "allowProjectileHits": false,
    "isInvulnerable": true,
    "canDespawn": false,
    "interaction": {
        "type": "dialogue",
        "dialogue": "cobblemon:blue_interaction"
    },
    "config": [
        {
            "variableName": "on_player_loses",
            "displayName": "npc.variable.on_player_loses.name",
            "description": "npc.variable.on_player_loses.desc",
            "type": "TEXT",
            "defaultValue": "q.run_script('cobblemon:generic_forfeit');"
        },
        {
            "variableName": "can_rechallenge",
            "displayName": "Rechallenging",
            "description": "This NPC can be battled multiple times.",
            "type": "BOOLEAN",
            "defaultValue": true
        },
        {
            "variableName": "on_player_wins",
            "displayName": "npc.variable.on_player_wins.name",
            "description": "npc.variable.on_player_wins.desc",
            "type": "TEXT",
            "defaultValue": "q.run_command('execute as ' + q.player.username + ' run opendialogue bluegym_end @s');"
          }
    ],
    "names": [
        "Blue"
    ],
    "battleConfiguration": {
        "canChallenge": true
    },
    "party": {
        "type": "simple",
        "pokemon": [
            "Exeggutor level=55 moves=leafstorm,psychic,hypnosis,trickroom",
            "Arcanine level=58 moves=roar,dragonpulse,flareblitz,extremespeed",
            "Rhydon level=58 moves=megahorn,stoneedge,thunderfang,earthquake",
            "Gyarados level=52 moves=icefang,waterfall,dragondance,return",
            "Machamp level=56 moves=dynamicpunch,earthquake,stoneedge,thunderpunch",
            "Pidgeot level=60 moves=return,whirlwind,airslash,mirrormove"
        ]
    },
    "ai": [

        {
            "type": "add_tasks_to_activity",
            "activity": "core",
            "tasksByPriority": {
                "0": [
                    "look_at_target",
                    "stay_afloat"
                ]
            }
        },
        {
            "type": "add_tasks_to_activity",
            "activity": "idle",
            "tasksByPriority": {
                "0": [
                    "look_at_target"
                ],
                "1": [
                    "look_at_entities"
                ]
            }
        }
    ]
}